odoo10_addon_web_widget_slick_example-10.0.1.0.0-py2.7-nspkg.pth
odoo/addons/web_widget_slick_example/README.rst
odoo/addons/web_widget_slick_example/__init__.py
odoo/addons/web_widget_slick_example/__manifest__.py
odoo/addons/web_widget_slick_example/demo/slick_example_data.xml
odoo/addons/web_widget_slick_example/models/__init__.py
odoo/addons/web_widget_slick_example/models/slick_example.py
odoo/addons/web_widget_slick_example/security/ir.model.access.csv
odoo/addons/web_widget_slick_example/static/description/icon.png
odoo/addons/web_widget_slick_example/static/description/icon.svg
odoo/addons/web_widget_slick_example/views/slick_example_view.xml
odoo10_addon_web_widget_slick_example-10.0.1.0.0.dist-info/DESCRIPTION.rst
odoo10_addon_web_widget_slick_example-10.0.1.0.0.dist-info/METADATA
odoo10_addon_web_widget_slick_example-10.0.1.0.0.dist-info/RECORD
odoo10_addon_web_widget_slick_example-10.0.1.0.0.dist-info/WHEEL
odoo10_addon_web_widget_slick_example-10.0.1.0.0.dist-info/metadata.json
odoo10_addon_web_widget_slick_example-10.0.1.0.0.dist-info/namespace_packages.txt
odoo10_addon_web_widget_slick_example-10.0.1.0.0.dist-info/top_level.txt
